setup.py
skuld/__init__.py
skuld/ec2skuld.py
skuld/skuld.py
skuld.egg-info/PKG-INFO
skuld.egg-info/SOURCES.txt
skuld.egg-info/dependency_links.txt
skuld.egg-info/entry_points.txt
skuld.egg-info/requires.txt
skuld.egg-info/top_level.txt