Metadata-Version: 1.1
Name: skuld
Version: 1.1.3
Summary: Generate an AWS profile with the 2FA authentication from CLI
Home-page: UNKNOWN
Author: Stanislas Nanchen
Author-email: stan@deep-impact.ch
License: Apache2
Keywords: AWS 2FA CLI
Platform: MacOS X; Linux
Classifier: Development Status :: 4 - Beta
Classifier: Intended Audience :: Developers
Classifier: Operating System :: MacOS :: MacOS X
Classifier: Operating System :: POSIX
Classifier: Programming Language :: Python
Classifier: Programming Language :: Python :: 3
Classifier: Programming Language :: Python :: 3.4
Classifier: Programming Language :: Python :: 3.5
Classifier: Programming Language :: Python :: 3.6
